jacks_menu/__init__.py
jacks_menu/__version__.py
jacks_menu/constants.py
jacks_menu/doc_id.py
jacks_menu/download.py
jacks_menu/export.py
jacks_menu/main.py
jacks_menu/menu.py
jacks_menu/parser.py
jacks_menu/py.typed
jacks_menu-0.1.4.dist-info/METADATA
jacks_menu-0.1.4.dist-info/WHEEL
jacks_menu-0.1.4.dist-info/entry_points.txt
jacks_menu-0.1.4.dist-info/licenses/LICENSE
jacks_menu-0.1.4.dist-info/RECORD
