Metadata-Version: 2.4
Name: jacks-menu
Version: 0.1.4
Summary: A tool to scrape the Jack's Gelato menu
Author-email: EdmundGoodman <egoodman3141@gmail.com>
License-Expression: MIT
License-File: LICENSE
Classifier: Development Status :: 2 - Pre-Alpha
Classifier: License :: OSI Approved :: MIT License
Classifier: Natural Language :: English
Classifier: Programming Language :: Python :: 3 :: Only
Classifier: Typing :: Typed
Requires-Python: >=3.10
Requires-Dist: click>=8.1.7
Requires-Dist: gdown>=5.2.0
Requires-Dist: python-dateutil>=2.9.0.post0
Requires-Dist: setuptools>=75.6.0
